{
  "checks": [
    {
      "check_id": "SYSTEM_VERSION",
      "detail": "0.5.0",
      "pass": true
    },
    {
      "check_id": "VECTOR_SET_ID",
      "detail": "secport_a392c25a59ae68f6505b183e26f96af64f842e30745df9e7ae9f68d895f99cd4",
      "pass": true
    },
    {
      "check_id": "VECTOR_CORPUS_ID",
      "detail": "sha256:720b5c795efef23489ed800fd0b7bb3d1ec2b2e6e20fe0ec9c0f2aeca54c5ae7",
      "pass": true
    },
    {
      "check_id": "SEC-PORT-RC001",
      "detail": "SEC-PORT-RC001",
      "pass": true
    },
    {
      "check_id": "SEC-PORT-RA001",
      "detail": "SEC-PORT-RA001",
      "pass": true
    },
    {
      "check_id": "SEC-PORT-RC002",
      "detail": "SEC-PORT-RC002",
      "pass": true
    },
    {
      "check_id": "SEC-PORT-RA002",
      "detail": "SEC-PORT-RA002",
      "pass": true
    },
    {
      "check_id": "SEC-PORT-RC003",
      "detail": "SEC-PORT-RC003",
      "pass": true
    },
    {
      "check_id": "SEC-PORT-RA003",
      "detail": "SEC-PORT-RA003",
      "pass": true
    },
    {
      "check_id": "SEC-PORT-RC004",
      "detail": "SEC-PORT-RC004",
      "pass": true
    },
    {
      "check_id": "SEC-PORT-RA004",
      "detail": "SEC-PORT-RA004",
      "pass": true
    },
    {
      "check_id": "SEC-PORT-SC001",
      "detail": "SEC-PORT-SC001",
      "pass": true
    },
    {
      "check_id": "SEC-PORT-SA001",
      "detail": "SEC-PORT-SA001",
      "pass": true
    },
    {
      "check_id": "SEC-PORT-SC002",
      "detail": "SEC-PORT-SC002",
      "pass": true
    },
    {
      "check_id": "SEC-PORT-SA002",
      "detail": "SEC-PORT-SA002",
      "pass": true
    },
    {
      "check_id": "SEC-PORT-SC003",
      "detail": "SEC-PORT-SC003",
      "pass": true
    },
    {
      "check_id": "SEC-PORT-SA003",
      "detail": "SEC-PORT-SA003",
      "pass": true
    },
    {
      "check_id": "SEC-PORT-FC001",
      "detail": "SEC-PORT-FC001",
      "pass": true
    },
    {
      "check_id": "SEC-PORT-FA001",
      "detail": "SEC-PORT-FA001",
      "pass": true
    },
    {
      "check_id": "SEC-PORT-FC002",
      "detail": "SEC-PORT-FC002",
      "pass": true
    },
    {
      "check_id": "SEC-PORT-FA002",
      "detail": "SEC-PORT-FA002",
      "pass": true
    },
    {
      "check_id": "SEC-PORT-FC003",
      "detail": "SEC-PORT-FC003",
      "pass": true
    },
    {
      "check_id": "SEC-PORT-FA003",
      "detail": "SEC-PORT-FA003",
      "pass": true
    },
    {
      "check_id": "SEC-PORT-CC001",
      "detail": "SEC-PORT-CC001",
      "pass": true
    },
    {
      "check_id": "SEC-PORT-CA001",
      "detail": "SEC-PORT-CA001",
      "pass": true
    },
    {
      "check_id": "SEC-PORT-DC001",
      "detail": "SEC-PORT-DC001",
      "pass": true
    },
    {
      "check_id": "SEC-PORT-DA001",
      "detail": "SEC-PORT-DA001",
      "pass": true
    }
  ],
  "evidence_id": "sha256:7b99708a80daf405825f5ca4aed764e0803a9eb38ed369a092c93e5f947e358f",
  "passed": 27,
  "schema": "SEC-STRUCTURAL-PORTABILITY-PARITY-EVIDENCE-1-D01",
  "status": "PASS",
  "system_version": "0.5.0",
  "total": 27,
  "vector_corpus_id": "sha256:720b5c795efef23489ed800fd0b7bb3d1ec2b2e6e20fe0ec9c0f2aeca54c5ae7",
  "vector_set_id": "secport_a392c25a59ae68f6505b183e26f96af64f842e30745df9e7ae9f68d895f99cd4"
}
